tasks_for_notebook
